napari_sift_registration/__init__.py
napari_sift_registration/_widget.py
napari_sift_registration/napari.yaml
napari_sift_registration-0.1.2.dist-info/LICENSE
napari_sift_registration-0.1.2.dist-info/METADATA
napari_sift_registration-0.1.2.dist-info/WHEEL
napari_sift_registration-0.1.2.dist-info/entry_points.txt
napari_sift_registration-0.1.2.dist-info/top_level.txt
napari_sift_registration-0.1.2.dist-info/RECORD
