Metadata-Version: 2.1
Name: napari-sift-registration
Version: 0.1.2
Summary: Simple plugin for SIFT keypoint detection, and affine registration with RANSAC, based on scikit-image
Home-page: https://github.com/jfozard/napari-sift-registration
Author: John Fozard
Author-email: john.fozard@gmail.com
License: BSD-3-Clause
Project-URL: Bug Tracker, https://github.com/jfozard/napari-sift-registration/issues
Project-URL: Documentation, https://github.com/jfozard/napari-sift-registration#README.md
Project-URL: Source Code, https://github.com/jfozard/napari-sift-registration
Project-URL: User Support, https://github.com/jfozard/napari-sift-registration/issues
Classifier: Development Status :: 3 - Alpha
Classifier: Intended Audience :: Developers
Classifier: Framework :: napari
Classifier: Topic :: Scientific/Engineering :: Image Processing
Classifier: Programming Language :: Python
Classifier: Programming Language :: Python :: 3
Classifier: Programming Language :: Python :: 3.8
Classifier: Programming Language :: Python :: 3.9
Classifier: Programming Language :: Python :: 3.10
Classifier: Operating System :: OS Independent
Classifier: License :: OSI Approved :: BSD License
Requires-Python: >=3.8
License-File: LICENSE
Requires-Dist: numpy
Requires-Dist: magicgui
Requires-Dist: qtpy
Requires-Dist: scikit-image
Provides-Extra: testing
Requires-Dist: tox ; extra == 'testing'
Requires-Dist: pytest ; extra == 'testing'
Requires-Dist: pytest-cov ; extra == 'testing'
Requires-Dist: pytest-qt ; extra == 'testing'
Requires-Dist: napari ; extra == 'testing'
Requires-Dist: pyqt5 ; extra == 'testing'
